cedalion/__init__.py
cedalion/_version.py
cedalion/datasets.py
cedalion/errors.py
cedalion/nirs.py
cedalion/physunits.py
cedalion/plots.py
cedalion/tasks.py
cedalion/testing.py
cedalion/typing.py
cedalion/utils.py
cedalion/validators.py
cedalion/vtktutils.py
cedalion/xrutils.py
cedalion/data/10-5-System_Mastoids_EGI129.tsv
cedalion/data/__init__.py
cedalion/data/measfunc_table.npy
cedalion/data/prahl_absorption_spectrum.tsv
cedalion/data/ninja_cap_probe/fullhead_56x144_System2_landmarks.tsv
cedalion/data/ninja_cap_probe/fullhead_56x144_System2_measlist.tsv
cedalion/data/ninja_cap_probe/fullhead_56x144_System2_optodes.tsv
cedalion/data/ninja_uhd_cap_probe/fullhead_164x496_landmarks.tsv
cedalion/data/ninja_uhd_cap_probe/fullhead_164x496_measlist.tsv
cedalion/data/ninja_uhd_cap_probe/fullhead_164x496_optodes.tsv
cedalion/dataclasses/__init__.py
cedalion/dataclasses/accessors.py
cedalion/dataclasses/geometry.py
cedalion/dataclasses/recording.py
cedalion/dataclasses/schemas.py
cedalion/geometry/__init__.py
cedalion/geometry/landmarks.py
cedalion/geometry/registration.py
cedalion/geometry/segmentation.py
cedalion/geometry/utils.py
cedalion/geometry/photogrammetry/__init__.py
cedalion/geometry/photogrammetry/processors.py
cedalion/imagereco/__init__.py
cedalion/imagereco/forward_model.py
cedalion/imagereco/solver.py
cedalion/imagereco/tissue_properties.py
cedalion/imagereco/utils.py
cedalion/io/__init__.py
cedalion/io/anatomy.py
cedalion/io/bids.py
cedalion/io/forward_model.py
cedalion/io/nirs.py
cedalion/io/photogrammetry.py
cedalion/io/probe_geometry.py
cedalion/io/snirf.py
cedalion/math/__init__.py
cedalion/math/ar_irls.py
cedalion/math/ar_model.py
cedalion/math/resample.py
cedalion/math/stats_helpers.py
cedalion/models/__init__.py
cedalion/models/glm/__init__.py
cedalion/models/glm/basis_functions.py
cedalion/models/glm/design_matrix.py
cedalion/models/glm/solve.py
cedalion/sigdecomp/ERBM.py
cedalion/sigdecomp/ICA_EBM.py
cedalion/sigdecomp/__init__.py
cedalion-25.1.0.dist-info/METADATA
cedalion-25.1.0.dist-info/WHEEL
cedalion-25.1.0.dist-info/licenses/LICENSE.md
cedalion-25.1.0.dist-info/RECORD
