Metadata-Version: 2.4
Name: cedalion
Version: 25.1.0
Summary: A fNIRS analysis framework
Project-URL: Home, https://ibs-lab.com/cedalion/
Project-URL: Documentation, https://doc.ibs.tu-berlin.de/cedalion/doc/dev/
Project-URL: Source Code, https://github.com/ibs-lab/cedalion/
Author: Eike Middell et al.
License-File: LICENSE.md
Classifier: Development Status :: 3 - Alpha
Classifier: Intended Audience :: Science/Research
Classifier: License :: OSI Approved :: MIT License
Classifier: Operating System :: OS Independent
Classifier: Programming Language :: Python
Classifier: Topic :: Scientific/Engineering :: Artificial Intelligence
Classifier: Topic :: Scientific/Engineering :: Medical Science Apps.
Requires-Python: >=3.11
Requires-Dist: click==8.2.*
Requires-Dist: h5py==3.14.*
Requires-Dist: ipympl
Requires-Dist: matplotlib==3.10.*
Requires-Dist: mne-bids==0.16.*
Requires-Dist: mne-nirs==0.7.*
Requires-Dist: mne==1.9.*
Requires-Dist: nibabel==5.3.*
Requires-Dist: nilearn==0.11.*
Requires-Dist: numpy==2.2.*
Requires-Dist: opencv-python>4
Requires-Dist: pandas==2.3.*
Requires-Dist: pint-xarray==0.4.*
Requires-Dist: pmcx==0.4.2
Requires-Dist: pmcxcl==0.3.1
Requires-Dist: pooch==1.8.*
Requires-Dist: pybids==0.19.*
Requires-Dist: pyvista==0.45.*
Requires-Dist: pywavefront==1.3.*
Requires-Dist: pywavelets==1.8.*
Requires-Dist: pyxdf==1.17.0
Requires-Dist: scikit-image==0.25.*
Requires-Dist: scikit-learn==1.7.*
Requires-Dist: scipy==1.15.*
Requires-Dist: seaborn==0.13.*
Requires-Dist: setuptools-scm
Requires-Dist: snirf==0.8.*
Requires-Dist: statsmodels==0.14.4
Requires-Dist: strenum==0.4.*
Requires-Dist: trame-components==2.5.*
Requires-Dist: trame-vtk==2.8.*
Requires-Dist: trame-vuetify==3.0.*
Requires-Dist: trame==3.10.*
Requires-Dist: trimesh==4.6.*
Requires-Dist: vtk>9.3
Requires-Dist: xarray==2025.6.*
